comfyui_idl-0.1.3.dist-info/METADATA
comfyui_idl-0.1.3.dist-info/WHEEL
comfyui_idl-0.1.3.dist-info/entry_points.txt
comfyui_idl-0.1.3.dist-info/licenses/LICENSE
comfyui_idl/__init__.py
comfyui_idl/cli.py
comfyui_idl/package.py
comfyui_idl/run.py
comfyui_idl/utils.py
comfyui_idl-0.1.3.dist-info/RECORD
