Metadata-Version: 2.1
Name: comfyui-idl
Version: 0.1.3
Summary: ComfyUI Interface Definition Language
Author-Email: Frost Ming <frost@bentoml.com>
Classifier: Programming Language :: Python :: 3
Classifier: License :: OSI Approved :: Apache Software License
Classifier: Operating System :: OS Independent
Project-URL: Homepage, https://github.com/bentoml/ComfyUI-IDL
Requires-Python: >=3.9
Requires-Dist: click>=8.1.7
Requires-Dist: comfy-cli>=1.2.8
Requires-Dist: pydantic>=2.9
